pycalci/__init__.py
pycalci/calculator.py
pycalci-0.1.1.dist-info/METADATA
pycalci-0.1.1.dist-info/WHEEL
pycalci-0.1.1.dist-info/entry_points.txt
pycalci-0.1.1.dist-info/top_level.txt
pycalci-0.1.1.dist-info/RECORD
