Metadata-Version: 2.1
Name: pycalci
Version: 0.1.1
Summary: UNKNOWN
Home-page: https://github.com/mugdhadalal/pycalci
Author: Mugdha Dalal
Author-email: mugdhadalal@gmail.com
License: UNKNOWN
Platform: UNKNOWN
Classifier: Natural Language :: English
Classifier: Programming Language :: Python :: 3.6
Classifier: Programming Language :: Python :: 3.7
Classifier: Programming Language :: Python :: 3 :: Only
Requires-Dist: fire (>=0.1.1)
